textfy/__init__.py
textfy/textfy.py
textfy-0.3.dist-info/METADATA
textfy-0.3.dist-info/WHEEL
textfy-0.3.dist-info/top_level.txt
textfy-0.3.dist-info/RECORD
