Metadata-Version: 2.1
Name: textfy
Version: 0.3
Summary: Send text message with Twilio
Home-page: https://github.com/ojy0216/textfy
Author: JuYoung Oh
Author-email: juyoung.oh@snu.ac.kr
License: MIT
Keywords: sms,twilio
Requires-Python: >=3
Requires-Dist: twilio (==7.16.1)
